osam_sam/__init__.py
osam_sam/_models.py
osam_sam-0.1.0.dist-info/METADATA
osam_sam-0.1.0.dist-info/WHEEL
osam_sam-0.1.0.dist-info/licenses/LICENSE
osam_sam-0.1.0.dist-info/RECORD
