Metadata-Version: 2.3
Name: osam-sam
Version: 0.1.0
Summary: Segment Anything Model for Osam.
Project-URL: Homepage, https://github.com/wkentaro/osam-sam
Author-email: Kentaro Wada <www.kentaro.wada@gmail.com>
License: Apache License 2.0
License-File: LICENSE
Classifier: Development Status :: 3 - Alpha
Classifier: Environment :: Console
Classifier: Intended Audience :: Developers
Classifier: License :: OSI Approved :: Apache Software License
Classifier: Operating System :: OS Independent
Classifier: Programming Language :: Python
Classifier: Programming Language :: Python :: 3 :: Only
Classifier: Programming Language :: Python :: 3.8
Classifier: Programming Language :: Python :: 3.9
Classifier: Programming Language :: Python :: 3.10
Classifier: Programming Language :: Python :: 3.11
Classifier: Programming Language :: Python :: 3.12
Classifier: Topic :: Software Development :: Libraries :: Python Modules
Requires-Python: >=3.8
Requires-Dist: osam-core
Requires-Dist: pillow
Provides-Extra: test
Requires-Dist: build; extra == 'test'
Requires-Dist: mypy; extra == 'test'
Requires-Dist: pytest; extra == 'test'
Requires-Dist: pytest-xdist; extra == 'test'
Requires-Dist: ruff; extra == 'test'
Requires-Dist: twine; extra == 'test'
